README.md
setup.py
prodistribution/Binomial_distribution.py
prodistribution/Gaussian_distribution.py
prodistribution/General_distribution.py
prodistribution/__init__.py
prodistribution.egg-info/PKG-INFO
prodistribution.egg-info/SOURCES.txt
prodistribution.egg-info/dependency_links.txt
prodistribution.egg-info/not-zip-safe
prodistribution.egg-info/top_level.txt