Metadata-Version: 2.1
Name: prodistribution
Version: 0.2
Summary: Gaussian and binomial distributions
Home-page: https://github.com/s0umitra/pypi-prodistribution
Author: Soumitra Edake
Author-email: souedake@gmail.com
License: MIT
Platform: UNKNOWN
Classifier: Programming Language :: Python :: 3
Classifier: License :: OSI Approved :: MIT License
Classifier: Operating System :: OS Independent
